LICENSE
MANIFEST.in
README.rst
setup.py
django_dsm_feedback.egg-info/PKG-INFO
django_dsm_feedback.egg-info/SOURCES.txt
django_dsm_feedback.egg-info/dependency_links.txt
django_dsm_feedback.egg-info/top_level.txt
feedback/__init__.py
feedback/admin.py
feedback/apps.py
feedback/models.py
feedback/tests.py
feedback/urls.py
feedback/views.py
feedback/migrations/0001_initial.py
feedback/migrations/0002_auto_20180430_1349.py
feedback/migrations/0003_feedback_page.py
feedback/migrations/__init__.py
feedback/static/feedback/bootstrap/css/bootstrap-grid.css
feedback/static/feedback/bootstrap/css/bootstrap-grid.css.map
feedback/static/feedback/bootstrap/css/bootstrap-grid.min.css
feedback/static/feedback/bootstrap/css/bootstrap-grid.min.css.map
feedback/static/feedback/bootstrap/css/bootstrap-reboot.css
feedback/static/feedback/bootstrap/css/bootstrap-reboot.css.map
feedback/static/feedback/bootstrap/css/bootstrap-reboot.min.css
feedback/static/feedback/bootstrap/css/bootstrap-reboot.min.css.map
feedback/static/feedback/bootstrap/css/bootstrap.css
feedback/static/feedback/bootstrap/css/bootstrap.css.map
feedback/static/feedback/bootstrap/css/bootstrap.min.css
feedback/static/feedback/bootstrap/css/bootstrap.min.css.map
feedback/static/feedback/bootstrap/js/bootstrap.bundle.js
feedback/static/feedback/bootstrap/js/bootstrap.bundle.js.map
feedback/static/feedback/bootstrap/js/bootstrap.bundle.min.js
feedback/static/feedback/bootstrap/js/bootstrap.bundle.min.js.map
feedback/static/feedback/bootstrap/js/bootstrap.js
feedback/static/feedback/bootstrap/js/bootstrap.js.map
feedback/static/feedback/bootstrap/js/bootstrap.min.js
feedback/static/feedback/bootstrap/js/bootstrap.min.js.map
feedback/static/feedback/custom/css/base.css
feedback/static/feedback/custom/imgs/flaticon/confused.svg
feedback/static/feedback/custom/imgs/flaticon/crying.svg
feedback/static/feedback/custom/imgs/flaticon/in-love.svg
feedback/static/feedback/custom/imgs/flaticon/sad.svg
feedback/static/feedback/custom/imgs/flaticon/sick.svg
feedback/static/feedback/custom/imgs/flaticon/smile.svg
feedback/static/feedback/custom/imgs/flaticon/star-struck.svg
