Metadata-Version: 1.1
Name: django-dsm-feedback
Version: 0.1
Summary: A simple Django app to gather feedback on your site.
Home-page: https://www.example.com/
Author: DSM
Author-email: sumner.magruder@zmnh.uni-hamburg.de
License: BSD License
Platform: UNKNOWN
Classifier: Environment :: Web Environment
Classifier: Framework :: Django
Classifier: Framework :: Django :: 2.0
Classifier: Intended Audience :: Developers
Classifier: License :: OSI Approved :: BSD License
Classifier: Operating System :: OS Independent
Classifier: Programming Language :: Python
Classifier: Programming Language :: Python :: 3.5
Classifier: Programming Language :: Python :: 3.6
Classifier: Topic :: Internet :: WWW/HTTP
Classifier: Topic :: Internet :: WWW/HTTP :: Dynamic Content
